shipdan_serializer_tester/__init__.py
shipdan_serializer_tester/model_serializer_tester.py
shipdan_serializer_tester-0.0.9.dist-info/METADATA
shipdan_serializer_tester-0.0.9.dist-info/WHEEL
shipdan_serializer_tester-0.0.9.dist-info/top_level.txt
shipdan_serializer_tester-0.0.9.dist-info/RECORD
